dynaphopy/__init__.py
dynaphopy/atoms.py
dynaphopy/displacements.cp310-win_amd64.pyd
dynaphopy/dynamics.py
dynaphopy/generate_cell.py
dynaphopy/parameters.py
dynaphopy/projection.py
dynaphopy/analysis/__init__.py
dynaphopy/analysis/coordinates.py
dynaphopy/analysis/energy.py
dynaphopy/analysis/modes.py
dynaphopy/analysis/peaksearch.py
dynaphopy/analysis/thermal_properties.py
dynaphopy/analysis/fitting/__init__.py
dynaphopy/analysis/fitting/fitting_functions.py
dynaphopy/interface/__init__.py
dynaphopy/interface/interactive_ui.py
dynaphopy/interface/lammps_link.py
dynaphopy/interface/phonopy_link.py
dynaphopy/interface/iofile/__init__.py
dynaphopy/interface/iofile/trajectory_parsers.py
dynaphopy/power_spectrum/__init__.py
dynaphopy/power_spectrum/correlation.cp310-win_amd64.pyd
dynaphopy/power_spectrum/mem.cp310-win_amd64.pyd
dynaphopy-1.18.0.data/scripts/concath5
dynaphopy-1.18.0.data/scripts/dynaphopy
dynaphopy-1.18.0.data/scripts/fitdata
dynaphopy-1.18.0.data/scripts/qha_extract
dynaphopy-1.18.0.data/scripts/rfc_calc
dynaphopy-1.18.0.dist-info/LICENSE
dynaphopy-1.18.0.dist-info/METADATA
dynaphopy-1.18.0.dist-info/WHEEL
dynaphopy-1.18.0.dist-info/top_level.txt
dynaphopy-1.18.0.dist-info/RECORD
