Metadata-Version: 2.4
Name: dynaphopy
Version: 1.18.0
Summary: dynaphopy module
Home-page: https://github.com/abelcarreras/DynaPhoPy
Author: Abel Carreras
Author-email: abelcarreras83@gmail.com
License: MIT License
License-File: LICENSE
Requires-Dist: phonopy
Requires-Dist: numpy
Requires-Dist: scipy
Requires-Dist: matplotlib
Dynamic: author
Dynamic: author-email
Dynamic: description
Dynamic: description-content-type
Dynamic: home-page
Dynamic: license
Dynamic: license-file
Dynamic: requires-dist
Dynamic: summary
